mindtorch/__init__.py
mindtorch/module_hooker.py
mindtorch/package_info.py
mindtorch/utils.py
mindtorch/tools/__init__.py
mindtorch/tools/convert_tensor.py
mindtorch/tools/debug_layer_info.py
mindtorch/tools/mstorch_enable.py
mindtorch/tools/pth2ckpt.py
mindtorch/tools/pytorch_enable.py
mindtorch/tools/support_wrap_ops.yaml
mindtorch/tools/utils.py
mindtorch/torch/__init__.py
mindtorch/torch/_default_dtype.py
mindtorch/torch/_export_func_to_root.py
mindtorch/torch/_linalg_utils.py
mindtorch/torch/_lowrank.py
mindtorch/torch/_patch_func.py
mindtorch/torch/_register_numpy_primitive.py
mindtorch/torch/_six.py
mindtorch/torch/_tensor.py
mindtorch/torch/_tensor_str.py
mindtorch/torch/_utils.py
mindtorch/torch/conflict_functional.py
mindtorch/torch/functional.py
mindtorch/torch/hub.py
mindtorch/torch/library.py
mindtorch/torch/logging.py
mindtorch/torch/overrides.py
mindtorch/torch/random.py
mindtorch/torch/serialization.py
mindtorch/torch/storage.py
mindtorch/torch/tensor.py
mindtorch/torch/tensor_type.py
mindtorch/torch/torch_version.py
mindtorch/torch/types.py
mindtorch/torch/_C/Generator.py
mindtorch/torch/_C/Size.py
mindtorch/torch/_C/__init__.py
mindtorch/torch/_ref/__init__.py
mindtorch/torch/_register/__init__.py
mindtorch/torch/_register/getitem_impl.py
mindtorch/torch/_register/register_multitype_ops.py
mindtorch/torch/_register/register_standard_method.py
mindtorch/torch/_register/register_utils.py
mindtorch/torch/amp/__init__.py
mindtorch/torch/amp/autocast_mode.py
mindtorch/torch/autograd/__init__.py
mindtorch/torch/autograd/function.py
mindtorch/torch/autograd/functional.py
mindtorch/torch/autograd/grad_mode.py
mindtorch/torch/autograd/variable.py
mindtorch/torch/backends/__init__.py
mindtorch/torch/backends/cuda/__init__.py
mindtorch/torch/backends/cudnn/__init__.py
mindtorch/torch/backends/mkl/__init__.py
mindtorch/torch/backends/mkldnn/__init__.py
mindtorch/torch/backends/mps/__init__.py
mindtorch/torch/backends/openmp/__init__.py
mindtorch-0.4.0.dist-info/LICENSE
mindtorch-0.4.0.dist-info/METADATA
mindtorch-0.4.0.dist-info/WHEEL
mindtorch-0.4.0.dist-info/top_level.txt
mindtorch-0.4.0.dist-info/RECORD
