Metadata-Version: 2.1
Name: mindtorch
Version: 0.4.0
Summary: MindTorch is a toolkit for support the PyTorch model running on Ascend.
Home-page: https://openi.pcl.ac.cn/OpenI/MSAdapter 
Author: Peng Cheng Lab, HUAWEI
Author-email: pcl.openi@pcl.ac.cn
License: Apache 2.0
Classifier: Development Status :: 3 - Alpha
Classifier: Programming Language :: Python :: 3 :: Only
Classifier: Programming Language :: Python :: 3.7
Classifier: Programming Language :: Python :: 3.8
Classifier: Intended Audience :: Developers
Classifier: Intended Audience :: Science/Research
Classifier: Intended Audience :: Information Technology
Classifier: License :: OSI Approved :: Apache Software License
Classifier: Topic :: Scientific/Engineering :: Artificial Intelligence
Classifier: Topic :: Software Development :: Libraries
Classifier: Topic :: Software Development :: Libraries :: Python Modules
Classifier: Operating System :: OS Independent
License-File: LICENSE
Requires-Dist: ml-dtypes ==0.2.0
Requires-Dist: numpy !=1.22.0,!=1.22.1,!=1.22.2,<2.0.0,>=1.20.0
Requires-Dist: numba <0.59,>=0.56.4
Requires-Dist: scikit-learn <1.3.0,>=1.0.2
Requires-Dist: librosa ==0.10.2
Requires-Dist: tqdm ==4.65.0
